pytest_explicit/__init__.py
pytest_explicit/py.typed
pytest_explicit-1.0.1.dist-info/LICENSE
pytest_explicit-1.0.1.dist-info/METADATA
pytest_explicit-1.0.1.dist-info/WHEEL
pytest_explicit-1.0.1.dist-info/entry_points.txt
pytest_explicit-1.0.1.dist-info/top_level.txt
pytest_explicit-1.0.1.dist-info/RECORD
