Metadata-Version: 2.1
Name: pytest-explicit
Version: 1.0.1
Summary: A Pytest plugin to ignore certain marked tests by default
Home-page: https://github.com/taliamax/pytest-explicit
Author: Natalia Maximo
Author-email: iam@natalia.dev
License: MIT License
Keywords: pytest,plugin
Platform: UNKNOWN
Classifier: Development Status :: 5 - Production/Stable
Classifier: Intended Audience :: Developers
Classifier: Operating System :: OS Independent
Classifier: Framework :: Pytest
Classifier: License :: OSI Approved :: MIT License
Classifier: Programming Language :: Python :: 3
Classifier: Programming Language :: Python :: 3.6
Classifier: Programming Language :: Python :: 3.7
Classifier: Programming Language :: Python :: 3.8
Classifier: Programming Language :: Python :: 3.9
Classifier: Topic :: Software Development :: Testing
Classifier: Typing :: Typed
Requires-Python: >=3.6
Requires-Dist: pytest
Provides-Extra: tests
Requires-Dist: flake8 ; extra == 'tests'
Requires-Dist: mypy ; extra == 'tests'
